texel/__init__.py
texel/__main__.py
texel/coordinate.py
texel/grid.py
texel/keys.py
texel/reader.py
texel/styles.py
texel/texel.py
texel/utils.py
texel-0.2.1.dist-info/LICENSE
texel-0.2.1.dist-info/METADATA
texel-0.2.1.dist-info/WHEEL
texel-0.2.1.dist-info/entry_points.txt
texel-0.2.1.dist-info/top_level.txt
texel-0.2.1.dist-info/RECORD
