Metadata-Version: 2.1
Name: texel
Version: 0.2.1
Summary: Command line interface for reading spreadsheets inside terminal.
Home-page: https://github.com/lauriat/texel
Author: Lauri Tuominen
Author-email: lauri.a.tuominen@gmail.com
License: UNKNOWN
Platform: UNKNOWN
Classifier: Programming Language :: Python :: 3
Classifier: License :: OSI Approved :: MIT License
Classifier: Operating System :: OS Independent
Requires-Python: >=3
License-File: LICENSE
Requires-Dist: openpyxl
Requires-Dist: odfpy
Requires-Dist: pyperclip
Requires-Dist: numpy
